llmcache/__init__.py
llmcache-0.0.1.dist-info/METADATA
llmcache-0.0.1.dist-info/WHEEL
llmcache-0.0.1.dist-info/top_level.txt
llmcache-0.0.1.dist-info/RECORD
